spheroids/__init__.py
spheroids/model.py
spheroids/cpp/__init__.py
spheroids/cpp/_estim.cp39-win_amd64.pyd
spheroids/cpp/_estim.cpp
spheroids/cpp/_utils.cp39-win_amd64.pyd
spheroids/cpp/_utils.cpp
spheroids-0.3.0.dist-info/LICENSE
spheroids-0.3.0.dist-info/METADATA
spheroids-0.3.0.dist-info/WHEEL
spheroids-0.3.0.dist-info/top_level.txt
spheroids-0.3.0.dist-info/RECORD
