Metadata-Version: 2.1
Name: spheroids
Version: 0.3.0
Summary: A package for spherical clustering and probabilistic modeling
Home-page: https://github.com/lsablica/spheroids
Author: Lukas Sablica
Author-email: Lukas Sablica <lsablica@wu.ac.at>
License: GNU GENERAL PUBLIC LICENSE
Requires-Python: >=3.8
License-File: LICENSE
Requires-Dist: pybind11
Requires-Dist: numpy
Requires-Dist: torch
Requires-Dist: matplotlib
